django_tgbot/__init__.py
django_tgbot/bot.py
django_tgbot/bot_api_user.py
django_tgbot/decorators.py
django_tgbot/exceptions.py
django_tgbot/models.py
django_tgbot/management/helpers.py
django_tgbot/management/bot_template/__init__.py
django_tgbot/management/bot_template/bot.py
django_tgbot/management/bot_template/credentials.py
django_tgbot/management/bot_template/models.py
django_tgbot/management/bot_template/processors.py
django_tgbot/management/bot_template/urls.py
django_tgbot/management/bot_template/views.py
django_tgbot/management/bot_template/migrations/0001_initial.py
django_tgbot/management/bot_template/migrations/__init__.py
django_tgbot/management/commands/createtgbot.py
django_tgbot/management/commands/tgbottoken.py
django_tgbot/management/commands/tgbotwebhook.py
django_tgbot/migrations/__init__.py
django_tgbot/state_manager/__init__.py
django_tgbot/state_manager/message_types.py
django_tgbot/state_manager/state.py
django_tgbot/state_manager/state_manager.py
django_tgbot/state_manager/state_types.py
django_tgbot/state_manager/transition_condition.py
django_tgbot/state_manager/update_types.py
django_tgbot/types/__init__.py
django_tgbot/types/animation.py
django_tgbot/types/audio.py
django_tgbot/types/botcommand.py
django_tgbot/types/callbackquery.py
django_tgbot/types/chat.py
django_tgbot/types/chatmember.py
django_tgbot/types/chatpermissions.py
django_tgbot/types/chatphoto.py
django_tgbot/types/choseninlineresult.py
django_tgbot/types/contact.py
django_tgbot/types/dice.py
django_tgbot/types/document.py
django_tgbot/types/encryptedcredentials.py
django_tgbot/types/encryptedpassportelement.py
django_tgbot/types/file.py
django_tgbot/types/forcereply.py
django_tgbot/types/game.py
django_tgbot/types/gamehighscore.py
django_tgbot/types/inlinekeyboardbutton.py
django_tgbot/types/inlinekeyboardmarkup.py
django_tgbot/types/inlinequery.py
django_tgbot/types/inlinequeryresult.py
django_tgbot/types/inputmessagecontent.py
django_tgbot/types/invoice.py
django_tgbot-2.0.0.dist-info/LICENSE
django_tgbot-2.0.0.dist-info/METADATA
django_tgbot-2.0.0.dist-info/WHEEL
django_tgbot-2.0.0.dist-info/top_level.txt
django_tgbot-2.0.0.dist-info/RECORD
